django_heroku/__init__.py
django_heroku/__version__.py
django_heroku/core.py
django_heroku-0.3.0.dist-info/DESCRIPTION.rst
django_heroku-0.3.0.dist-info/METADATA
django_heroku-0.3.0.dist-info/RECORD
django_heroku-0.3.0.dist-info/WHEEL
django_heroku-0.3.0.dist-info/metadata.json
django_heroku-0.3.0.dist-info/top_level.txt
