Metadata-Version: 2.0
Name: django-heroku
Version: 0.3.0
Summary: This is a Django library for Heroku apps.
Home-page: https://github.com/heroku/django-heroku
Author: Kenneth Reitz
Author-email: kreitz@salesforce.com
License: MIT
Platform: UNKNOWN
Classifier: License :: OSI Approved :: MIT License
Classifier: Programming Language :: Python
Classifier: Programming Language :: Python :: 2.6
Classifier: Programming Language :: Python :: 2.7
Classifier: Programming Language :: Python :: 3
Classifier: Programming Language :: Python :: 3.3
Classifier: Programming Language :: Python :: 3.4
Classifier: Programming Language :: Python :: 3.5
Classifier: Programming Language :: Python :: 3.6
Classifier: Programming Language :: Python :: Implementation :: CPython
Classifier: Programming Language :: Python :: Implementation :: PyPy
Requires-Dist: dj-database-url (>=0.5.0)
Requires-Dist: whitenoise
Requires-Dist: psycopg2
Requires-Dist: django
